{
    "Covid Donation": {
        "name": "Covid Donation",
        "id": "1QpNa_s4yI6z80v7HvmwvvEjCFuQ-QLrH",
        "title": "Covid Donations At Hospital",
        "date": "15.11.2020",
        "file_info": {
            "id": "1d_UJuev4KKp6lRzYSozexb900_fTzHo25--hbYWY80I",
            "name": "Covid Donation"
        },
        "img_links": [],
        "description": "Hello from the other side"
    },
    "Hlegu Donation": {
        "name": "Hlegu Donation",
        "id": "1LMKVZ15G8GZsyxprN-OkvCbhbfFA-0Cu",
        "title": "Donation In A Monastery From Hlegu",
        "date": "15.11.2020",
        "description": "Hello from the other side",
        "file_info": {
            "id": "19euOQZ6mfsv-c2OCHNZViwtkAg3wFlPVJUF2o2rOpDQ",
            "name": "donation in hlegu"
        },
        "img_links": [
            {
                "id": "1PYCdcuDmwxZ7jyawn3crCoGEvNfV-qLH",
                "name": "hlegu_donation_small_2.jpg"
            },
            {
                "id": "1hLF34NEYbzlHWdHg3HiAwZh-y1ct4Dph",
                "name": "hlegu_donation_small_1.jpg"
            },
            {
                "id": "1BjhGzujjuteP2glnH54Hki09ES2ghzP3",
                "name": "hlegu_donation_big.jpg"
            }
        ]
    }
}